palpao/__init__.py
palpao/__version__.py
palpao/calibration/__init__.py
palpao/calibration/abstract_calibration_manager.py
palpao/calibration/calibration_manager.py
palpao/calibration/in_memory_calibration_manager.py
palpao/client/__init__.py
palpao/client/abstract_deformable_mirror_client.py
palpao/client/deformable_mirror_client.py
palpao/client/simulated_deformable_mirror_client.py
palpao/types/__init__.py
palpao/types/deformable_mirror_status.py
palpao/types/modal_basis.py
palpao/utils/__init__.py
palpao/utils/constants.py
palpao/utils/timeout.py
palpao-0.17.0.dist-info/LICENSE
palpao-0.17.0.dist-info/METADATA
palpao-0.17.0.dist-info/WHEEL
palpao-0.17.0.dist-info/entry_points.txt
palpao-0.17.0.dist-info/top_level.txt
palpao-0.17.0.dist-info/RECORD
