Metadata-Version: 2.1
Name: palpao
Version: 0.17.0
Summary: ALPAO, Boston MEMS, Physik Instrument Deformable mirrors interface
Home-page: https://github.com/lbusoni/plico_dm
Author: Lorenzo Busoni
Author-email: lorenzo.busoni@inaf.it
License: MIT
Keywords: plico, deformable mirror, ALPAO, Boston MEMS, Physik Instrument, piezo, laboratory, instrumentation control
Platform: UNKNOWN
Classifier: Development Status :: 4 - Beta
Classifier: Operating System :: POSIX :: Linux
Classifier: Programming Language :: Python :: 2.7
Classifier: Programming Language :: Python :: 3.5
Classifier: Programming Language :: Python :: 3.6
License-File: LICENSE
Requires-Dist: plico (>=0.20)
Requires-Dist: numpy
Requires-Dist: six
Requires-Dist: astropy
